collagraph/__init__.py
collagraph/__main__.py
collagraph/collagraph.py
collagraph/component.py
collagraph/constants.py
collagraph/fragment.py
collagraph/weak.py
collagraph/__pyinstaller/__init__.py
collagraph/__pyinstaller/hook-collagraph.py
collagraph/renderers/__init__.py
collagraph/renderers/dict_renderer.py
collagraph/renderers/pygfx_renderer.py
collagraph/renderers/pyside_renderer.py
collagraph/renderers/pyside/__init__.py
collagraph/renderers/pyside/objects/__init__.py
collagraph/renderers/pyside/objects/combobox.py
collagraph/renderers/pyside/objects/dialogbuttonbox.py
collagraph/renderers/pyside/objects/dockwidget.py
collagraph/renderers/pyside/objects/itemmodel.py
collagraph/renderers/pyside/objects/layouts.py
collagraph/renderers/pyside/objects/listview.py
collagraph/renderers/pyside/objects/menu.py
collagraph/renderers/pyside/objects/menubar.py
collagraph/renderers/pyside/objects/qobject.py
collagraph/renderers/pyside/objects/scrollarea.py
collagraph/renderers/pyside/objects/splitter.py
collagraph/renderers/pyside/objects/standarditem.py
collagraph/renderers/pyside/objects/statusbar.py
collagraph/renderers/pyside/objects/tab.py
collagraph/renderers/pyside/objects/toolbar.py
collagraph/renderers/pyside/objects/treewidget.py
collagraph/renderers/pyside/objects/treewidgetitem.py
collagraph/renderers/pyside/objects/widget.py
collagraph/renderers/pyside/objects/window.py
collagraph/sfc/__init__.py
collagraph/sfc/compiler.py
collagraph/sfc/importer.py
collagraph/sfc/parser.py
collagraph-0.8.10.dist-info/METADATA
collagraph-0.8.10.dist-info/WHEEL
collagraph-0.8.10.dist-info/entry_points.txt
collagraph-0.8.10.dist-info/licenses/LICENSE
collagraph-0.8.10.dist-info/RECORD
