Metadata-Version: 2.4
Name: collagraph
Version: 0.8.10
Summary: Reactive user interfaces
Author-email: Berend Klein Haneveld <berendkleinhaneveld@gmail.com>, Korijn van Golen <korijn@gmail.com>
License-Expression: MIT
License-File: LICENSE
Requires-Python: >=3.10
Requires-Dist: observ>=0.17.1
Provides-Extra: pygfx
Requires-Dist: pygfx>=0.9.0; extra == 'pygfx'
Provides-Extra: pyside
Requires-Dist: pyside6!=6.8.3,!=6.9.0,>=6.6.2; (python_version < '3.15') and extra == 'pyside'
